{
    "keep": {
        "days": true,
        "amount": 1
    },
    "auditLog": "/app/config/logs/.20136e5b8544ec13f7fc29ce3d35150d597108bb-audit.json",
    "files": [
        {
            "date": 1782051709824,
            "name": "/app/config/logs/.machinelogs-2026-06-21.json",
            "hash": "74fbeb1df821b48f35c67fc37ad54f4308b54bf921789a3635876f350d62998f"
        },
        {
            "date": 1782086400017,
            "name": "/app/config/logs/.machinelogs-2026-06-22.json",
            "hash": "1190fa2c3e5182d426479f4e449104da9dc83ff67dbdeeb8b3528431c1d2fcf1"
        }
    ],
    "hashType": "sha256"
}